README.md
setup.py
glidetools/__init__.py
glidetools/construct_graph.py
glidetools.egg-info/PKG-INFO
glidetools.egg-info/SOURCES.txt
glidetools.egg-info/dependency_links.txt
glidetools.egg-info/entry_points.txt
glidetools.egg-info/requires.txt
glidetools.egg-info/top_level.txt
glidetools/algorithm/__init__.py
glidetools/algorithm/dsd.py
glidetools/algorithm/glide.py
glidetools/algorithm/local.py
glidetools/commands/__init__.py
glidetools/commands/glide_main.py