Metadata-Version: 2.1
Name: glidetools
Version: 0.0.4.post2
Summary: DSD, GLIDE and GLIDER tools
Home-page: https://github.com/kap-devkota/GLIDER
Author: Kapil Devkota
Author-email: kapil.devkota@tufts.edu
License: UNKNOWN
Platform: UNKNOWN
